hello_nbdev/__init__.py
hello_nbdev/_modidx.py
hello_nbdev/core.py
hello_nbdev_z-0.0.1.dist-info/LICENSE
hello_nbdev_z-0.0.1.dist-info/METADATA
hello_nbdev_z-0.0.1.dist-info/WHEEL
hello_nbdev_z-0.0.1.dist-info/entry_points.txt
hello_nbdev_z-0.0.1.dist-info/top_level.txt
hello_nbdev_z-0.0.1.dist-info/RECORD
